LICENSE
MANIFEST.in
README
example_dict.txt
ez_setup.py
setup.cfg
setup.py
stdeb.cfg
version.txt
YABT/__init__.py
YABT/app.py
YABT/basicContextTypes.py
YABT/exceptions.py
YABT/loaders.py
YABT/rules.py
YABT/translators.py
YABT.egg-info/PKG-INFO
YABT.egg-info/SOURCES.txt
YABT.egg-info/dependency_links.txt
YABT.egg-info/entry_points.txt
YABT.egg-info/top_level.txt
YABT/tables/britishtobrl.xml
YABT/tables/britishtounicodebrl.xml
docs/BasicExample.txt
docs/WritingWordDictionaryTables.txt
docs/WritingXMLTranslationTables.txt
tests/__init__.py
tests/run_tests.py
tests/YABT/__init__.py
tests/YABT/badlyformed.xml
tests/YABT/correct.xml
tests/YABT/loaders.py
tests/YABT/translators.py
tests/test_data/nonxml.trans