Metadata-Version: 1.0
Name: YABT
Version: 2.0.2
Summary: YABT: A context sensitive string manipulation tool
Home-page: http://yabt.berlios.de
Author: Michael Whapples
Author-email: mwhapples@users.berlios.de
License: RPL
Platform: UNKNOWN
Classifier: Development Status :: 5 - Production/Stable
Classifier: Intended Audience :: Developers
Classifier: License :: OSI Approved
Classifier: Operating System :: OS Independent
Classifier: Programming Language :: Python
Classifier: Topic :: Adaptive Technologies
Classifier: Topic :: Software Development
